pipx_isolate/__init__.py
pipx_isolate/__main__.py
pipx_isolate/py.typed
pipx_isolate-0.1.1.dist-info/licenses/LICENSE
pipx_isolate-0.1.1.dist-info/METADATA
pipx_isolate-0.1.1.dist-info/WHEEL
pipx_isolate-0.1.1.dist-info/entry_points.txt
pipx_isolate-0.1.1.dist-info/top_level.txt
pipx_isolate-0.1.1.dist-info/RECORD
