Metadata-Version: 2.4
Name: pipx_isolate
Version: 0.1.1
Summary: a pipx script installer supporting inline metadata for python scripts
Author: purarue
License-Expression: MIT
Project-URL: Homepage, https://github.com/purarue/pipx_isolate
Classifier: Programming Language :: Python
Classifier: Programming Language :: Python :: 3
Classifier: Programming Language :: Python :: 3 :: Only
Classifier: Programming Language :: Python :: 3.10
Classifier: Programming Language :: Python :: 3.11
Classifier: Programming Language :: Python :: 3.12
Classifier: Programming Language :: Python :: 3.13
Classifier: Programming Language :: Python :: 3.14
Requires-Python: >=3.10
License-File: LICENSE
Requires-Dist: click>=8.1.7
Provides-Extra: testing
Requires-Dist: flake8; extra == "testing"
Requires-Dist: mypy; extra == "testing"
Dynamic: license-file
